odoo/addons/project_task_name_with_id/README.rst
odoo/addons/project_task_name_with_id/__init__.py
odoo/addons/project_task_name_with_id/__manifest__.py
odoo/addons/project_task_name_with_id/i18n/it.po
odoo/addons/project_task_name_with_id/i18n/project_task_name_with_id.pot
odoo/addons/project_task_name_with_id/models/__init__.py
odoo/addons/project_task_name_with_id/models/project_task.py
odoo/addons/project_task_name_with_id/readme/CONTRIBUTORS.md
odoo/addons/project_task_name_with_id/readme/DESCRIPTION.md
odoo/addons/project_task_name_with_id/readme/USAGE.md
odoo/addons/project_task_name_with_id/static/description/icon.png
odoo/addons/project_task_name_with_id/static/description/index.html
odoo/addons/project_task_name_with_id/tests/__init__.py
odoo/addons/project_task_name_with_id/tests/test_project_task_id.py
odoo/addons/project_task_name_with_id/views/project_task_views.xml
odoo_addon_project_task_name_with_id-18.0.1.0.0.2.dist-info/METADATA
odoo_addon_project_task_name_with_id-18.0.1.0.0.2.dist-info/WHEEL
odoo_addon_project_task_name_with_id-18.0.1.0.0.2.dist-info/top_level.txt
odoo_addon_project_task_name_with_id-18.0.1.0.0.2.dist-info/RECORD
